atai_web_tool/__init__.py
atai_web_tool/cli.py
atai_web_tool/user_agents.py
atai_web_tool-0.0.9.dist-info/LICENSE
atai_web_tool-0.0.9.dist-info/METADATA
atai_web_tool-0.0.9.dist-info/WHEEL
atai_web_tool-0.0.9.dist-info/entry_points.txt
atai_web_tool-0.0.9.dist-info/top_level.txt
atai_web_tool-0.0.9.dist-info/RECORD
