Metadata-Version: 2.2
Name: atai-web-tool
Version: 0.0.9
Summary: Extract the main content from a webpage using Playwright, readability-lxml, and BeautifulSoup.
Home-page: https://github.com/AtomGradient/atai-web-tool
Author: AtomGradient
Author-email: AtomGradient <alex@atomgradient.com>
Project-URL: Homepage, https://github.com/AtomGradient/atai-web-tool
Classifier: Programming Language :: Python :: 3
Classifier: Operating System :: OS Independent
Requires-Python: >=3.6
License-File: LICENSE
Requires-Dist: playwright
Requires-Dist: readability-lxml
Requires-Dist: beautifulsoup4
Requires-Dist: lxml[html_clean]
Requires-Dist: newspaper4k
Dynamic: author
Dynamic: home-page
Dynamic: requires-python
